{
    "bg":"texture/locations/dahlem/dormEntry.jpg",
    "label":"Dorm",
    "text":"Dorm.",
    "rl":[
        {
            "locationId":"SELF.exterior",
            "time": 60,
            "label":"Outside"
        },
        {
            "locationId":"SELF.living",
            "time": 30
        },
        {
            "locationId":"SELF.kitchen",
            "time": 30
        },
        {
            "locationId":"SELF.bureau",
            "time": 30
        },
        {
            "locationId":"SELF.floor2",
            "time": 20,
            "label":"2nd Floor",
            "textureDisabled":true
        },
        {
            "locationId":"SELF.floor3",
            "time": 40,
            "label":"3rd Floor",
            "textureDisabled":true
        },
        {
            "locationId":"SELF.floor4",
            "time": 60,
            "label":"4th Floor",
            "textureDisabled":true
        },
        {
            "locationId":"SELF.floor5",
            "time": 80,
            "label":"5th Floor",
            "textureDisabled":true
        }
    ]
}